
  [
    {
      "name": "play 5",
      "state": true,
      "price": 659,
      "tags": "lifestyle",
      "img": "https://cdn.idealo.com/folder/Product/201490/2/201490239/s11_produktbild_gross_1/sony-playstation-5-ps5.jpg"
    },
    {
      "name": "xbox",
      "state": false,
      "price": 559,
      "tags": "lifestyle",
      "img": "https://res.cloudinary.com/grover/image/upload/f_webp,q_auto/b_white,c_pad,dpr_2.0,h_500,w_520/f_auto,q_auto/v1599665929/e99kmldr95rf9p40k4pu.png"
    },
    {
      "name": "nike",
      "state": true,
      "price": 180,
      "tags": "lifestyle",
      "img": "https://resize.sprintercdn.com/f/550x550/products/0319947/nike-revolution-6_0319947_00_4_4044725947.jpg"
    },
    {
      "name": "silla",
      "state": false,
      "price": 400,
      "tags": [
        "work",
        "lifestyle"
      ],
      "img": "https://media.trmuebles.com/product/silla-gaming-pro-800x800_C9k5T8M.jpg"
    },
    {
      "name": "reloj",
      "state": false,
      "price": 500,
      "tags": "lifestyle",
      "img": "https://www.worten.es/i/869564e52fbc4c1f66b4beda5f01c03ff1f67c06.jpg"
    },
    {
      "name": "pc",
      "state": true,
      "price": 1500,
      "tags": [
        "work",
        "lifestyle"
      ],
      "img": "https://d10mhq06fikmnr.cloudfront.net/catalog/product/h/u/hunter_rev2_os_rgb-min_4_1_1_1.jpg"
    },
    {
      "name": "apple",
      "state": true,
      "price": 1100,
      "tags": "mobile",
      "img": "https://store.storeimages.cdn-apple.com/4668/as-images.apple.com/is/refurb-iphone-12-black-2020?wid=1144&hei=1144&fmt=jpeg&qlt=90&.v=1635202741000"
    },
    {
      "name": "oppo",
      "state": false,
      "price": 450,
      "tags": "mobile",
      "img": "https://assets.mmsrg.com/isr/166325/c1/-/ASSET_MP_92469692/fee_786_587_png"
    },
    {
      "name": "yamaha R7",
      "state": true,
      "price": 10500,
      "tags": "motor",
      "img": "https://motos-b60.kxcdn.com/sites/default/files/yamaha-r7-2022.jpg"
    },
    {
      "name": "escritorio",
      "state": true,
      "price": 120,
      "tags": "work",
      "img": "https://img.furniture1.eu/v7/_im_/detailed/2947/2947616.jpg?w=900&h=675&p=fw"
    },
    {
      "name": "renault",
      "state": false,
      "price": 17000,
      "tags": "motor",
      "img": "https://images.coches.com/_vn_/renault/Clio/674171eb98d8b108125eca298fbd5735.jpg?p=cc_vn_medium"
    }
  ]
  